Workbook

Sheet Step One Know the Basics
B1: Guide2Go Steps to Overseas Travel WORKBOOK
B3: Instructions: Fill in the white cells following the Steps to Overseas Guide.
B4: STEP ONE: Know the Basics
B5: 1. Who is going?
B6: Names | D6: me, Aldo, Julien
B7: Number of people Do not include people under age 2 | D7: 3
B8: 2. What time of year are you going?
B9: Spring
B10: 3. How long are you going?
B11: 2 weeks
B12: 4. Where are you going?
B13: City | C13: Country | D13: Number of nights per city
B14: Paris | C14: France | D14: 3
B15: Lyon | C15: France | D15: 2
B16: Bordeaux | C16: France | D16: 2
B17: Barcelona | C17: Spain | D17: 3
B18: Madrid | C18: Spain | D18: 2
B20: Total number of nights | D20: =SUM(D14:D19) -> 12
B21: Total number of days | D21: =D20+1 -> 13

Sheet Step Two Afford and Save
B1: Guide2Go Steps to Overseas Travel WORKBOOK | I1: The earliest date I can book the flights is
I2: If using cash only for flights, the earliest date I can book flights is
B3: Instructions: Fill in the white cells following the Steps to Overseas Guide.
B4: Update cells 10 and 130 every month.
B5: STEP TWO: Afford and Save
B6: 1. Flight costs - Consider completing both strategies and choosing the best one.
B7: Strategy 1: Use credit card points or a combination of points and cash.
B8: Which credit card am I using? | E8: Chase Sapphire
B9: How many points do I need to save for everyone's flights there and back? | E9: 200000
B10: How many points do I have now? **Update this amount every month** | E10: 25000
B11: Remaining points needed. | E11: =E9-E10 -> 175000
B12: How many points will I earn each month? | E12: 15000
B13: Number of months to save all the points. | E13: =E9/E12 -> 13.333333
B14: Months left to save all the points. | E14: =E11/E12 -> 11.666667
B15: Strategy 2: Use cash only.
B16: How much will everyone's flights there and back cost? | E16: 4500
B17: How much cash do I have now for flights? | E17: 500
B18: Remaining cash needed. | E18: =E16-E17 -> 4000
B19: How much cash can I save per month for flights? | E19: 400
B20: Number of months to save total amount. | E20: =E16/E19 -> 11.25
B21: Months left to save total amount. | E21: =E18/E19 -> 10
B22: Decide: Which strategy did I choose?
B23: Points
B24: If using points, add estimate of any cash needed (taxes, fees, etc.) | E24: 700
B25: Total estimated flight cost | E25: =IF(B23="Cash only",E16,E24) -> 700
B26: 2. Housing costs
B27: Cities | C27: Total cost per city | D27: ='Step One Know the Basics'!D19
B28: ='Step One Know the Basics'!B14 -> Paris | C28: 625
B29: ='Step One Know the Basics'!B15 -> Lyon | C29: 275
B30: ='Step One Know the Basics'!B16 -> Bordeaux | C30: 425
B31: ='Step One Know the Basics'!B17 -> Barcelona | C31: 700
B32: ='Step One Know the Basics'!B18 -> Madrid | C32: 350
B33: ='Step One Know the Basics'!B19
B34: Total estimated housing cost | E34: =SUM(C28+C29+C30+C31+C32+C33) -> 2375
B35: 3. Food costs
B36: Total number of days | E36: ='Step One Know the Basics'!D21 -> 13
B37: Number of days eating budget meals | E37: 8
B38: Number of days eating moderate meals | E38: 6
B39: Estimated cost | E39: =(E37*50)+(E38*80)*'Step One Know the Basics'!D7 -> 1840
B40: Number of days in expensive countries | E40: 0
B41: Total estimated food cost | E41: =(E40*100)+E39 -> 1840
B42: 4. Transportation costs
B43: Transportation you will book in advance
B44: Trains from city to city | E44: Total cost
B45: Paris | C45: to | D45: Lyon | E45: 750
B46: Lyon | C46: to | D46: Bordeaux | E46: 350
B47: Bordeaux | C47: to | D47: Barcelona | E47: 400
B48: Barcelona | C48: to | D48: Madrid | E48: 400
C49: to
B50: Include any other planned transportation | E50: Total cost
B51: Paris river boat tour | E51: 300
B53: Flight from Madrid to London | E53: 500
B56: Total amount - Transportation you will book in advance | E56: =E45+E46+E47+E48+E49+E51+E52+E53+E54+E55 -> 2700
B57: Transportation you will buy during the trip
B58: To and from the airport | E58: 200
B59: Getting around the city - public transportation | E59: ='Step One Know the Basics'!D7*('Step One Know the Basics'!D21*30) -> 1170
B60: Getting around the city - rideshare | E60: =75*'Step One Know the Basics'!D21 -> 975
B61: Total amount - Buying during the trip | E61: =SUM(E58:E60) -> 2345
B62: Total transportation cost | E62: =SUM(E56+E61) -> 5045
B63: 5. Fun costs
B64: Planned cost - List the major activities you plan to do | E64: Total cost
B65: ='Step One Know the Basics'!B14 -> Paris
B66: Louvre | E66: 72
B67: Eiffel Tower | E67: 72
B68: Musée d'Orsay | E68: 51
B69: Sainte-Chapelle | E69: 0
B70: Clothes shopping | E70: 300
B73: ='Step One Know the Basics'!B15 -> Lyon
B74: Théâtres Romains de Fourvière | E74: 40
B75: Musée des Confluences | E75: 50
B76: Basilique Notre Dame de Fourviere | E76: 15
B81: ='Step One Know the Basics'!B16 -> Bordeaux
B82: Musée du Vin et du Négoce | E82: 40
B83: Bassins de Lumières | E83: 25
B84: Wine tasting | E84: 150
B89: ='Step One Know the Basics'!B17 -> Barcelona
B90: Basílica de la Sagrada Familia | E90: 25
B91: Casa Batlló | E91: 40
B92: Casa Vicens Gaudí | E92: 45
B93: Siteseeing Bus Tour | E93: 140
B97: ='Step One Know the Basics'!B18 -> Madrid
B98: Toledo tour | E98: 300
B99: Prado National Museum | E99: 75
B100: Museo Sorolla | E100: 40
B105: ='Step One Know the Basics'!B19
B113: Total amount - Booking fun in advance | E113: =SUM(E66:E112) -> 1480
B114: Total unplanned cost for extra activities (includes souvenirs) | E114: ='Step One Know the Basics'!D21*'Step One Know the Basics'!D7*30 -> 1170
B115: Total estimated fun cost | E115: =SUM(E113+E114) -> 2650
B116: 6. Trip preparation costs
B117: List what I need to buy for the trip | E117: Total cost
B118: Coats ($100 each) for 3 people | E118: 300
B119: New luggage | E119: 200
B120: Winter boots for 2 people ($100 and $150) | E120: 250
B125: Total estimated preparation cost | E125: =SUM(E118:E124) -> 750
B126: 7. Catch-all costs
B127: My total catch-all cost | E127: ='Step One Know the Basics'!D7*250 -> 750
B128: My total estimated trip cost is | E128: =E25+E34+E41+E62+E115+E125+E127 -> 14110
B129: How much can I save per month? | E129: 602
B130: How much do I have saved now? **Update this amount every month.** | E130: 500
B131: Amount left to save. | E131: =MAX(0, E128-E130) -> 13610
...

Sheet Step Three Book Your Trip
B1: Guide2Go Steps to Overseas Travel WORKBOOK
B3: Instructions: Fill in the white cells following the Steps to Overseas Guide.
B4: STEP THREE: Book Your Trip
B5: 1. Booking flights
B6: Airline | D6: American Airlines
B7: Outbound flight date | D7: 46089
B8: Return flight date | D8: 46102
B9: Did I reserve the seats? | D9: No
B10: Did I pay for checked bags? | D10: Yes
B11: Are all passports valid within 6 months from the end date of my trip? | D11: Yes
B12: If going to Europe, did I complete the ETIAS travel authorization? | D12: No
B13: What did I pay for the flights, including bags and seats? | D13: Total Amount Paid: Flights | F13: 700
D14: Amount I am under or over (red) budget for flights | F14: ='Step Two Afford and Save'!E25-F13 -> 0
B15: If I'm over budget: If I choose to save more, I must save this much more per month. | D15: =ABS(F14/'Step Two Afford and Save'!E132) -> 0
B16: 2. Booking housing
B17: City | C17: ='Step One Know the Basics'!B14 -> Paris
B18: Housing name | C18: Paris Court Hotel
B19: Dates | C19: 3/9/26-3/12/26
B20: Amount Paid | C20: 625
B21: City | C21: ='Step One Know the Basics'!B15 -> Lyon
B22: Housing name | C22: Best Western Lyon
B23: Dates | C23: 3/12/26-3/14/26
B24: Amount Paid | C24: 275
B25: City | C25: ='Step One Know the Basics'!B16 -> Bordeaux
B26: Housing name | C26: Airbnb Bordeaux
B27: Dates | C27: 3/14/26-3/16/26
B28: Amount Paid | C28: 450
B29: City | C29: ='Step One Know the Basics'!B17 -> Barcelona
B30: Housing name | C30: Hotel Mosaic
B31: Dates | C31: 3/16/26-3/19/26
B32: Amount Paid | C32: 725
B33: City | C33: ='Step One Know the Basics'!B18 -> Madrid
B34: Housing name | C34: Madrid Hotel
B35: Dates | C35: 3/19/26-3/21/26
B36: Amount Paid | C36: 300
B37: City | C37: ='Step One Know the Basics'!B19
B38: Housing name
B39: Dates
B40: Amount Paid
B41: Total Amount Paid: Housing | D41: =C20+C24+C28+C32+C36+C40 -> 2375
B42: Amount left from my estimate | D42: ='Step Two Afford and Save'!E34-D41 -> 0
B43: If I'm over budget: If I choose to save more, I must save this much more per month. | D43: =ABS(D42/'Step Two Afford and Save'!E132) -> 0
B44: 3. Food
B45: If you want to make any reservations at in-demand restaurants, document those here:
B46: Made a reservation for 3 at the Botin Restaurant in Madrid on 3/19 at 6pm using their website: https://botin.es/reserva/
B47: 4. Booking transportation
B48: Trains from city to city | E48: Check if booked | F48: Amount spent
B49: ='Step Two Afford and Save'!B45 -> Paris | C49: to | D49: ='Step Two Afford and Save'!D45 -> Lyon | E49: TRUE | F49: 770
B50: ='Step Two Afford and Save'!B46 -> Lyon | C50: to | D50: ='Step Two Afford and Save'!D46 -> Bordeaux | E50: TRUE | F50: 325
B51: ='Step Two Afford and Save'!B47 -> Bordeaux | C51: to | D51: ='Step Two Afford and Save'!D47 -> Barcelona | E51: TRUE | F51: 415
B52: ='Step Two Afford and Save'!B48 -> Barcelona | C52: to | D52: ='Step Two Afford and Save'!D48 -> Madrid | E52: TRUE | F52: 600
B53: ='Step Two Afford and Save'!B49 | C53: to | D53: ='Step Two Afford and Save'!D49 | E53: FALSE
B54: Include any other planned transportation | E54: Check if booked | F54: Amount spent
B55: ='Step Two Afford and Save'!B51 -> Paris river boat tour | E55: TRUE | F55: 200
B56: ='Step Two Afford and Save'!B52 | E56: FALSE
B57: ='Step Two Afford and Save'!B53 -> Flight from Madrid to London | E57: TRUE | F57: 400
B58: ='Step Two Afford and Save'!B54 | E58: FALSE
B59: ='Step Two Afford and Save'!B55 | E59: FALSE
B60: Total Amount Paid: Transportation | D60: =SUM(F49:G53,F55:G59) -> 2710
B61: Amount left from my estimate | D61: ='Step Two Afford and Save'!E56-D60 -> -10
B62: If I'm over budget: If I choose to save more, I must save this much more per month. | D62: =ABS(D61/'Step Two Afford and Save'!E132) -> 0.44232182
B63: 5. Booking fun
B64: Major activities planned | E64: Did I book? | F64: Amount spent or plan to spend
B65: ='Step One Know the Basics'!B14 -> Paris
B66: ='Step Two Afford and Save'!B66 -> Louvre | E66: TRUE | F66: 72
B67: ='Step Two Afford and Save'!B67 -> Eiffel Tower | E67: TRUE | F67: 70
B68: ='Step Two Afford and Save'!B68 -> Musée d'Orsay | E68: TRUE | F68: 49
B69: ='Step Two Afford and Save'!B69 -> Sainte-Chapelle | E69: TRUE | F69: 0
B70: ='Step Two Afford and Save'!B70 -> Clothes shopping | E70: FALSE | F70: 300
B71: ='Step Two Afford and Save'!B71 | E71: FALSE
B72: ='Step Two Afford and Save'!B72 | E72: FALSE
B73: ='Step Two Afford and Save'!B73 -> Lyon
B74: ='Step Two Afford and Save'!B74 -> Théâtres Romains de Fourvière | E74: TRUE | F74: 40
B75: ='Step Two Afford and Save'!B75 -> Musée des Confluences | E75: TRUE | F75: 50
B76: ='Step Two Afford and Save'!B76 -> Basilique Notre Dame de Fourviere | E76: TRUE | F76: 14
B77: ='Step Two Afford and Save'!B77 | E77: FALSE
B78: ='Step Two Afford and Save'!B78 | E78: FALSE
B79: ='Step Two Afford and Save'!B79 | E79: FALSE
B80: ='Step Two Afford and Save'!B80 | E80: FALSE
B81: ='Step Two Afford and Save'!B81 -> Bordeaux
B82: ='Step Two Afford and Save'!B82 -> Musée du Vin et du Négoce | E82: FALSE | F82: 40
B83: ='Step Two Afford and Save'!B83 -> Bassins de Lumières | E83: TRUE | F83: 24
B84: ='Step Two Afford and Save'!B84 -> Wine tasting | E84: TRUE | F84: 150
B85: ='Step Two Afford and Save'!B85 | E85: FALSE
B86: ='Step Two Afford and Save'!B86 | E86: FALSE
B87: ='Step Two Afford and Save'!B87 | E87: FALSE
B88: ='Step Two Afford and Save'!B88 | E88: FALSE
B89: ='Step Two Afford and Save'!B89 -> Barcelona
B90: ='Step Two Afford and Save'!B90 -> Basílica de la Sagrada Familia | E90: TRUE | F90: 65
B91: ='Step Two Afford and Save'!B91 -> Casa Batlló | E91: TRUE | F91: 40
B92: ='Step Two Afford and Save'!B92 -> Casa Vicens Gaudí | E92: TRUE | F92: 43
B93: ='Step Two Afford and Save'!B93 -> Siteseeing Bus Tour | E93: FALSE | F93: 140
B94: ='Step Two Afford and Save'!B94 | E94: FALSE
B95: ='Step Two Afford and Save'!B95 | E95: FALSE
B96: ='Step Two Afford and Save'!B96 | E96: FALSE
B97: ='Step Two Afford and Save'!B97 -> Madrid
B98: ='Step Two Afford and Save'!B98 -> Toledo tour | E98: TRUE | F98: 275
B99: ='Step Two Afford and Save'!B99 -> Prado National Museum | E99: FALSE | F99: 75
B100: ='Step Two Afford and Save'!B100 -> Museo Sorolla | E100: TRUE | F100: 45
B101: ='Step Two Afford and Save'!B101 | E101: FALSE
...

Sheet Final Trip Summary
B1: Guide2Go Steps to Overseas Travel WORKBOOK
B4: Trip Summary and Trip Budget
B5: Who is going?
B6: ='Step One Know the Basics'!D6 -> me, Aldo, Julien
B7: Flight Information
B8: Airline | E8: ='Step Three Book Your Trip'!D6 -> American Airlines
B9: Outbound flight date | E9: ='Step Three Book Your Trip'!D7 -> 46089
B10: Return flight date | E10: ='Step Three Book Your Trip'!D8 -> 46102
B11: Where are we going and staying?
B12: ='Step Three Book Your Trip'!C17 -> Paris | D12: ='Step Three Book Your Trip'!C21 -> Lyon | F12: ='Step Three Book Your Trip'!C25 -> Bordeaux
B13: ='Step Three Book Your Trip'!C18 -> Paris Court Hotel | D13: ='Step Three Book Your Trip'!C22 -> Best Western Lyon | F13: ='Step Three Book Your Trip'!C26 -> Airbnb Bordeaux
B14: ='Step Three Book Your Trip'!C29 -> Barcelona | D14: ='Step Three Book Your Trip'!C33 -> Madrid | F14: ='Step Three Book Your Trip'!C37
B15: ='Step Three Book Your Trip'!C30 -> Hotel Mosaic | D15: ='Step Three Book Your Trip'!C34 -> Madrid Hotel | F15: ='Step Three Book Your Trip'!C38
B16: Total amount spent: Pre-Trip | E16: ='Step Three Book Your Trip'!E130 -> 8087
B17: Total planned spending: During the Trip | E17: =SUM('Step Three Book Your Trip'!E131:G134) -> 6105
B18: Amount I can spend on food | E18: ='Step Three Book Your Trip'!E131 -> 1840
B19: Amount I can spend on non-reserved transportation | E19: ='Step Three Book Your Trip'!E132 -> 2345
B20: Amount I can spend on non-reserved fun | E20: ='Step Three Book Your Trip'!E133 -> 1170
B21: Catch-all cost | E21: ='Step Three Book Your Trip'!E134 -> 750
